pyvarnam/__init__.py
pyvarnam/constants.py
pyvarnam/library.py
pyvarnam/utils.py
pyvarnam/varnam.py
pyvarnam/varnam_defs.py
tests/__init__.py
tests/test.py
pyvarnam-1.0.0.dist-info/LICENSE
pyvarnam-1.0.0.dist-info/METADATA
pyvarnam-1.0.0.dist-info/WHEEL
pyvarnam-1.0.0.dist-info/top_level.txt
pyvarnam-1.0.0.dist-info/RECORD
