Metadata-Version: 2.1
Name: pyvarnam
Version: 1.0.0
Summary: Pyvarnam provides python bindings for libvarnam
Home-page: https://github.com/sebinthomas/pyvarnam
Author: Sebin Thomas
Author-email: me@sebin.in
License: MIT
Platform: UNKNOWN
Classifier: Topic :: Text Processing :: Linguistic
Classifier: Programming Language :: Python :: 3
Classifier: License :: OSI Approved :: MIT License
Requires-Python: >3.0
Requires-Dist: setuptools
